{
  "type" : [ "h-entry" ],
  "properties" : {
    "name" : [ "How to Be Good at Small Talk | Nobody Panic on Acast" ],
    "summary" : [ "Small talk can be excruciating but don’t worry! Stevie and Tessa have found some top tips that will make that terrifying networking event/party fly be. Or just be a little less arse-clenchy. Produced and edited by Ben Williams for Plosive Productions. Photos by Marco Vittur, jingle by David Dobson. Follow Nobody Panic on Twitter @NobodyPanicPod Be part of the Nobody Panic Patreon gang Support this show http://supporter.acast.com/nobodypanic. See acast.com/privacy for privacy and opt-out information." ],
    "featured" : [ "https://assets.pippa.io/shows/61ba04511a8cbe646c3cf0ca/61ba0470f75b72001244695f.jpg" ],
    "audio" : [ "https://sphinx.acast.com/nobodypanic/howtobegoodatsmalltalkr/media.mp3" ],
    "url" : [ "https://play.acast.com/s/nobodypanic/howtobegoodatsmalltalk" ]
  }
}
