{
  "type" : [ "h-entry" ],
  "properties" : {
    "name" : [ "APIs You Won't Hate | Funding Open Source with Dudley Carr from Stack Aid " ],
    "summary" : [ "Mike chats with Co-Founder of Stack Aid, Dudley Carr, about the importance of funding Open Source projects, and Stack Aid's approach to helping Open Source organizations get paid." ],
    "featured" : [ "https://images.transistor.fm/file/transistor/images/show/6533/medium_1576863269-artwork.jpg" ],
    "audio" : [ "https://media.transistor.fm/9bb11fc4/64055dea.mp3" ],
    "url" : [ "https://share.transistor.fm/s/9bb11fc4" ]
  }
}
