{
  "properties" : {
    "author" : [ {
      "properties" : {
        "location" : [ {
          "properties" : {
            "name" : [ "Wellington City, New Zealand" ]
          },
          "type" : [ "h-card", "p-location" ]
        } ],
        "name" : [ "Matthew @SwordsComic" ],
        "nickname" : [ "_mjwills" ],
        "numeric-id" : [ "18576332" ],
        "photo" : [ "https://pbs.twimg.com/profile_images/1471632116161024006/evnLrrBs.jpg" ],
        "published" : [ "2009-01-03T08:31:07+00:00" ],
        "uid" : [ "tag:twitter.com:_mjwills" ],
        "url" : [ "https://twitter.com/_mjwills", "https://linktr.ee/swordscomic" ]
      },
      "type" : [ "h-card" ]
    } ],
    "content" : [ "Choosing violence" ],
    "photo" : [ "https://pbs.twimg.com/media/FIPwq0cVUAI83Lf.jpg" ],
    "published" : [ "2022-01-04T08:59:41+00:00" ],
    "uid" : [ "tag:twitter.com:1478290023141101568" ],
    "url" : [ "https://twitter.com/_mjwills/status/1478290023141101568" ]
  },
  "type" : [ "h-entry" ]
}
