{
  "properties" : {
    "author" : [ {
      "properties" : {
        "location" : [ {
          "properties" : {
            "name" : [ "they area" ]
          },
          "type" : [ "h-card", "p-location" ]
        } ],
        "name" : [ "atomly" ],
        "nickname" : [ "atomly" ],
        "numeric-id" : [ "5529162" ],
        "photo" : [ "https://pbs.twimg.com/profile_images/1294075858877988865/UV7DCybR.jpg" ],
        "published" : [ "2007-04-26T14:37:09+00:00" ],
        "uid" : [ "tag:twitter.com:atomly" ],
        "url" : [ "https://twitter.com/atomly", "http://www.atomly.com/" ]
      },
      "type" : [ "h-card" ]
    } ],
    "content" : [ "one of the best messages i ever received from my mom was about this guy at costco with a hot dog in every pocket of his cargo shorts" ],
    "photo" : [ "https://pbs.twimg.com/media/FnBMN6hakAAFjJ4.jpg", "https://pbs.twimg.com/media/FnBMN6jakAE_OyH.jpg" ],
    "published" : [ "2023-01-21T19:11:10+00:00" ],
    "uid" : [ "tag:twitter.com:1616876072565624832" ],
    "url" : [ "https://twitter.com/atomly/status/1616876072565624832" ]
  },
  "type" : [ "h-entry" ]
}
