{
  "properties" : {
    "author" : [ {
      "properties" : {
        "name" : [ "bencord0" ],
        "nickname" : [ "bencord0" ],
        "numeric-id" : [ "16199761" ],
        "photo" : [ "https://pbs.twimg.com/profile_images/1016770575610601472/XdhC26yq.jpg" ],
        "published" : [ "2008-09-09T08:42:45+00:00" ],
        "uid" : [ "tag:twitter.com:bencord0" ],
        "url" : [ "https://twitter.com/bencord0", "http://blog.rebornco.de" ]
      },
      "type" : [ "h-card" ]
    } ],
    "content" : [ {
      "html" : "<div style=\"white-space: pre\">you should write/publish it anyway\n\nMaybe yours has a different API, or uses different dependencies.\n\nAlso, you'll have it in your backpocket if anything unfortunate happens to the other one.</div>\n<a class=\"u-mention\" aria-hidden=\"true\" href=\"https://twitter.com/JamieTanna\"></a>",
      "value" : "you should write/publish it anyway\n\nMaybe yours has a different API, or uses different dependencies.\n\nAlso, you'll have it in your backpocket if anything unfortunate happens to the other one."
    } ],
    "in-reply-to" : [ "https://twitter.com/JamieTanna/status/1576472740919447553" ],
    "published" : [ "2022-10-02T08:13:58+00:00" ],
    "uid" : [ "tag:twitter.com:1576485629612806144" ],
    "url" : [ "https://twitter.com/bencord0/status/1576485629612806144" ]
  },
  "type" : [ "h-entry" ]
}
