{
  "properties" : {
    "author" : [ {
      "properties" : {
        "location" : [ {
          "properties" : {
            "name" : [ "Online" ]
          },
          "type" : [ "h-card", "p-location" ]
        } ],
        "name" : [ "Kat Cosgrove" ],
        "nickname" : [ "Dixie3Flatline" ],
        "numeric-id" : [ "835996764" ],
        "photo" : [ "https://pbs.twimg.com/profile_images/1483456365960089603/p-J7gZwI.jpg" ],
        "published" : [ "2012-09-20T17:27:21+00:00" ],
        "uid" : [ "tag:twitter.com:Dixie3Flatline" ],
        "url" : [ "https://twitter.com/Dixie3Flatline", "https://linktr.ee/katcosgrove" ]
      },
      "type" : [ "h-card" ]
    } ],
    "content" : [ {
      "html" : "Hi there! Go fuck yourself.\n<a class=\"u-mention\" aria-hidden=\"true\" href=\"https://twitter.com/mattstratton\"></a>\n<a class=\"u-mention\" aria-hidden=\"true\" href=\"https://twitter.com/mbritton\"></a>",
      "value" : "Hi there! Go fuck yourself."
    } ],
    "in-reply-to" : [ "https://twitter.com/mbritton/status/1533158136034611200" ],
    "published" : [ "2022-06-04T19:21:36+00:00" ],
    "uid" : [ "tag:twitter.com:1533167100767920134" ],
    "url" : [ "https://twitter.com/Dixie3Flatline/status/1533167100767920134" ]
  },
  "type" : [ "h-entry" ]
}
