{
  "properties" : {
    "author" : [ {
      "properties" : {
        "location" : [ {
          "properties" : {
            "name" : [ "hopeless brexit kingdom" ]
          },
          "type" : [ "h-card", "p-location" ]
        } ],
        "name" : [ "laura" ],
        "nickname" : [ "freezydorito" ],
        "numeric-id" : [ "3004020255" ],
        "photo" : [ "https://pbs.twimg.com/profile_images/1582830852890890270/iLZgh40-.jpg" ],
        "published" : [ "2015-01-29T10:06:54+00:00" ],
        "uid" : [ "tag:twitter.com:freezydorito" ],
        "url" : [ "https://twitter.com/freezydorito", "https://www.laura.monster" ]
      },
      "type" : [ "h-card" ]
    } ],
    "content" : [ {
      "html" : "look if this went past me it’s going past the entire target audience for high on life\n<a class=\"u-mention\" aria-hidden=\"true\" href=\"https://twitter.com/BaneNook\"></a>",
      "value" : "look if this went past me it’s going past the entire target audience for high on life"
    } ],
    "in-reply-to" : [ "https://twitter.com/BaneNook/status/1604225875419222016" ],
    "published" : [ "2022-12-17T21:27:51+00:00" ],
    "uid" : [ "tag:twitter.com:1604226895335362561" ],
    "url" : [ "https://twitter.com/freezydorito/status/1604226895335362561" ]
  },
  "type" : [ "h-entry" ]
}
