{
  "properties" : {
    "author" : [ {
      "properties" : {
        "name" : [ "Georgia Tennant" ],
        "nickname" : [ "georgiaEtennant" ],
        "numeric-id" : [ "884649543777886209" ],
        "photo" : [ "https://pbs.twimg.com/profile_images/884652864764825600/r0O4kj_F.jpg" ],
        "published" : [ "2017-07-11T05:44:22+00:00" ],
        "uid" : [ "tag:twitter.com:georgiaEtennant" ],
        "url" : [ "https://twitter.com/georgiaEtennant", "http://badpennyproductions.com/" ]
      },
      "type" : [ "h-card" ]
    } ],
    "photo" : [ "https://pbs.twimg.com/media/FiAtbisXkAEYT84.jpg" ],
    "published" : [ "2022-11-20T13:38:12+00:00" ],
    "uid" : [ "tag:twitter.com:1594324230002335744" ],
    "url" : [ "https://twitter.com/georgiaEtennant/status/1594324230002335744" ]
  },
  "type" : [ "h-entry" ]
}
