{
  "properties" : {
    "author" : [ {
      "properties" : {
        "name" : [ "Molly White" ],
        "nickname" : [ "molly0xFFF" ],
        "numeric-id" : [ "545445165" ],
        "photo" : [ "https://pbs.twimg.com/profile_images/1488233929438027785/xxHMHmJQ.jpg" ],
        "published" : [ "2012-04-04T19:00:12+00:00" ],
        "uid" : [ "tag:twitter.com:molly0xFFF" ],
        "url" : [ "https://twitter.com/molly0xFFF", "https://www.mollywhite.net/linktree" ]
      },
      "type" : [ "h-card" ]
    } ],
    "content" : [ {
      "html" : "<div style=\"white-space: pre\">to anyone who's thinking about buying github copilot:\n\njust be warned that it may have been trained on code i wrote</div>",
      "value" : "to anyone who's thinking about buying github copilot:\n\njust be warned that it may have been trained on code i wrote"
    } ],
    "published" : [ "2022-06-22T19:25:55+00:00" ],
    "uid" : [ "tag:twitter.com:1539691169080393729" ],
    "url" : [ "https://twitter.com/molly0xFFF/status/1539691169080393729" ]
  },
  "type" : [ "h-entry" ]
}
