{
  "properties" : {
    "author" : [ {
      "properties" : {
        "location" : [ {
          "properties" : {
            "name" : [ "New York City" ]
          },
          "type" : [ "h-card", "p-location" ]
        } ],
        "name" : [ "The New York Times" ],
        "nickname" : [ "nytimes" ],
        "numeric-id" : [ "807095" ],
        "photo" : [ "https://pbs.twimg.com/profile_images/1098244578472280064/gjkVMelR.png" ],
        "published" : [ "2007-03-02T20:41:42+00:00" ],
        "uid" : [ "tag:twitter.com:nytimes" ],
        "url" : [ "https://twitter.com/nytimes", "http://www.nytimes.com/", "http://nyti.ms/2FVHq9v" ]
      },
      "type" : [ "h-card" ]
    } ],
    "content" : [ {
      "html" : "A California bakery spent a month making a 6-foot recreation of Han Solo frozen in carbonite, made entirely of bread. The mother-and-daughter duo behind the creation called him \"Pan Solo.\" <a href=\"https://nyti.ms/3EHVqS0\">nyti.ms/3EHVqS0</a>",
      "value" : "A California bakery spent a month making a 6-foot recreation of Han Solo frozen in carbonite, made entirely of bread. The mother-and-daughter duo behind the creation called him \"Pan Solo.\" nyti.ms/3EHVqS0"
    } ],
    "photo" : [ {
      "alt" : "An image of \"Pan Solo,\" a 6-foot recreation of Han Solo frozen in carbonite that is made entirely out of bread. Photo by Hannalee Pervan.",
      "value" : "https://pbs.twimg.com/media/FfHPfpmXoAEi-r1.jpg"
    } ],
    "published" : [ "2022-10-15T13:17:38+00:00" ],
    "uid" : [ "tag:twitter.com:1581273090763653121" ],
    "url" : [ "https://twitter.com/nytimes/status/1581273090763653121" ]
  },
  "type" : [ "h-entry" ]
}
