{
  "properties" : {
    "author" : [ {
      "properties" : {
        "location" : [ {
          "properties" : {
            "name" : [ "Earth" ]
          },
          "type" : [ "h-card", "p-location" ]
        } ],
        "name" : [ "Harshit" ],
        "nickname" : [ "planetravelover" ],
        "numeric-id" : [ "1432239130944049158" ],
        "photo" : [ "https://pbs.twimg.com/profile_images/1432290456218439680/rpH8wEbx.jpg" ],
        "published" : [ "2021-08-30T07:10:03+00:00" ],
        "uid" : [ "tag:twitter.com:planetravelover" ],
        "url" : [ "https://twitter.com/planetravelover" ]
      },
      "type" : [ "h-card" ]
    } ],
    "content" : [ {
      "html" : "<div style=\"white-space: pre\">Wordle 259 X/6\n\nTried ‘crine’ in the last attempt <a href=\"https://twitter.com/search?q=%23Wordle\">#Wordle</a> <a href=\"https://twitter.com/search?q=%23Wordle259\">#Wordle259</a></div>",
      "value" : "Wordle 259 X/6\n\nTried ‘crine’ in the last attempt #Wordle #Wordle259"
    } ],
    "photo" : [ "https://pbs.twimg.com/media/FND5u1VacAINCti.jpg" ],
    "published" : [ "2022-03-05T05:01:09+00:00" ],
    "uid" : [ "tag:twitter.com:1499973265741459456" ],
    "url" : [ "https://twitter.com/planetravelover/status/1499973265741459456" ]
  },
  "type" : [ "h-entry" ]
}
