{
  "children" : [ {
    "properties" : {
      "author" : [ {
        "properties" : {
          "location" : [ {
            "properties" : {
              "name" : [ "😌" ]
            },
            "type" : [ "h-card", "p-location" ]
          } ],
          "name" : [ "worms cited" ],
          "nickname" : [ "christapeterso" ],
          "numeric-id" : [ "292438708" ],
          "photo" : [ "https://pbs.twimg.com/profile_images/1514650435642007579/lsdxzOz_.jpg" ],
          "published" : [ "2011-05-03T17:06:18+00:00" ],
          "uid" : [ "tag:twitter.com:christapeterso" ],
          "url" : [ "https://twitter.com/christapeterso" ]
        },
        "type" : [ "h-card" ]
      } ],
      "content" : [ {
        "html" : "<div style=\"white-space: pre\">i spent 2 hours curating a twitter blue screenshot storyline for my parents so here u go, for your own offline friends that want to have fun:\n\nDAY 1 – ARRIVAL</div>",
        "value" : "i spent 2 hours curating a twitter blue screenshot storyline for my parents so here u go, for your own offline friends that want to have fun:\n\nDAY 1 – ARRIVAL"
      } ],
      "photo" : [ {
        "alt" : "Elon Musk\n@elonmusk\nEntering Twitter HQ - let that sink in!\n[video of him arriving at twitter carrying a heavy porcelain sink]\n\nElon Musk\nReplying to @elonmusk\nMeeting a lot of cool people at Twitter today!",
        "value" : "https://pbs.twimg.com/media/FhkMaQqUYAIuMWN.jpg"
      } ],
      "published" : [ "2022-11-15T00:44:32+00:00" ],
      "uid" : [ "tag:twitter.com:1592317592966168576" ],
      "url" : [ "https://twitter.com/christapeterso/status/1592317592966168576" ]
    },
    "type" : [ "u-quotation-of", "h-cite" ]
  } ],
  "properties" : {
    "author" : [ {
      "properties" : {
        "location" : [ {
          "properties" : {
            "name" : [ "Portland, Oregon USA" ]
          },
          "type" : [ "h-card", "p-location" ]
        } ],
        "name" : [ "Rich Burroughs @ $8chan" ],
        "nickname" : [ "richburroughs" ],
        "numeric-id" : [ "19552154" ],
        "photo" : [ "https://pbs.twimg.com/profile_images/1200607261082705920/HMNZOqa-.jpg" ],
        "published" : [ "2009-01-26T19:35:35+00:00" ],
        "uid" : [ "tag:twitter.com:richburroughs" ],
        "url" : [ "https://twitter.com/richburroughs", "https://linktr.ee/richburroughs" ]
      },
      "type" : [ "h-card" ]
    } ],
    "content" : [ "It’s really something to see these all laid out in one thread. I missed seeing some of these tweets, despite being extremely online." ],
    "published" : [ "2022-11-15T06:40:39+00:00" ],
    "uid" : [ "tag:twitter.com:1592407210319286274" ],
    "url" : [ "https://twitter.com/richburroughs/status/1592407210319286274" ]
  },
  "type" : [ "h-entry" ]
}
