{
  "children" : [ {
    "properties" : {
      "author" : [ {
        "properties" : {
          "location" : [ {
            "properties" : {
              "name" : [ "Arkansas, USA" ]
            },
            "type" : [ "h-card", "p-location" ]
          } ],
          "name" : [ "RAMZPAUL" ],
          "nickname" : [ "ramzpaul" ],
          "numeric-id" : [ "53979469" ],
          "photo" : [ "https://pbs.twimg.com/profile_images/1591074150696865792/4tQhJQFu.jpg" ],
          "published" : [ "2009-07-05T19:12:52+00:00" ],
          "uid" : [ "tag:twitter.com:ramzpaul" ],
          "url" : [ "https://twitter.com/ramzpaul", "http://www.ramzpaul.com", "http://tinyurl.com/kgy7zcl", "http://ramzpaul.gumroad.com/l/wfezh" ]
        },
        "type" : [ "h-card" ]
      } ],
      "content" : [ "In the 1970s, many men supported the sexual revolution because they thought they would benefit from many easy women. That was true, but only for the top 20%." ],
      "photo" : [ "https://pbs.twimg.com/media/FifcHnLWQAUif2p.jpg" ],
      "published" : [ "2022-11-26T12:50:45+00:00" ],
      "uid" : [ "tag:twitter.com:1596486619263303681" ],
      "url" : [ "https://twitter.com/ramzpaul/status/1596486619263303681" ]
    },
    "type" : [ "u-quotation-of", "h-cite" ]
  } ],
  "properties" : {
    "author" : [ {
      "properties" : {
        "location" : [ {
          "properties" : {
            "name" : [ "\"august\"：they/21/CA/slow DMs" ]
          },
          "type" : [ "h-card", "p-location" ]
        } ],
        "name" : [ "https://linktr.ee/boyzantium" ],
        "nickname" : [ "SAMOYEDWAVE" ],
        "numeric-id" : [ "1000328182208303104" ],
        "photo" : [ "https://pbs.twimg.com/profile_images/1563133672865218560/iRw76wZb.png" ],
        "published" : [ "2018-05-26T10:49:58+00:00" ],
        "uid" : [ "tag:twitter.com:SAMOYEDWAVE" ],
        "url" : [ "https://twitter.com/SAMOYEDWAVE", "http://discord.gg/woof" ]
      },
      "type" : [ "h-card" ]
    } ],
    "content" : [ "i'm assembling a team " ],
    "photo" : [ "https://pbs.twimg.com/media/FiklHqOVsAET4Yk.png" ],
    "published" : [ "2022-11-27T12:48:44+00:00" ],
    "uid" : [ "tag:twitter.com:1596848496224522240" ],
    "url" : [ "https://twitter.com/SAMOYEDWAVE/status/1596848496224522240" ]
  },
  "type" : [ "h-entry" ]
}
