{
  "properties" : {
    "author" : [ {
      "properties" : {
        "location" : [ {
          "properties" : {
            "name" : [ "hell is real" ]
          },
          "type" : [ "h-card", "p-location" ]
        } ],
        "name" : [ "lucky devil" ],
        "nickname" : [ "SatansJacuzzi" ],
        "numeric-id" : [ "612760470" ],
        "photo" : [ "https://pbs.twimg.com/profile_images/1469514347806433285/JSdu0YkI.jpg" ],
        "published" : [ "2012-06-19T16:34:20+00:00" ],
        "uid" : [ "tag:twitter.com:SatansJacuzzi" ],
        "url" : [ "https://twitter.com/SatansJacuzzi", "https://www.haymarketbooks.org/books/1518-no-planet-b" ]
      },
      "type" : [ "h-card" ]
    } ],
    "content" : [ "\"i'm not queer\" well, david, queer is historically a political position emphasizing solidarity between sexual and gender minorities in resistance to oppression, and you're explicitly more interested into assimilating into straightness. so yeah, we know." ],
    "published" : [ "2022-10-19T20:30:27+00:00" ],
    "uid" : [ "tag:twitter.com:1582831567482691586" ],
    "url" : [ "https://twitter.com/SatansJacuzzi/status/1582831567482691586" ]
  },
  "type" : [ "h-entry" ]
}
