{
  "properties" : {
    "author" : [ {
      "properties" : {
        "location" : [ {
          "properties" : {
            "name" : [ "Liverpool" ]
          },
          "type" : [ "h-card", "p-location" ]
        } ],
        "name" : [ "lil nass x" ],
        "nickname" : [ "sheevpaIps" ],
        "numeric-id" : [ "1266562241391984640" ],
        "photo" : [ "https://pbs.twimg.com/profile_images/1449470400585478144/pdcDGBPb.jpg" ],
        "published" : [ "2020-05-30T02:49:26+00:00" ],
        "uid" : [ "tag:twitter.com:sheevpaIps" ],
        "url" : [ "https://twitter.com/sheevpaIps" ]
      },
      "type" : [ "h-card" ]
    } ],
    "content" : [ "oh my god this is so well made" ],
    "location" : [ {
      "properties" : {
        "name" : [ "Liverpool, England" ],
        "uid" : [ "tag:twitter.com:151b9e91272233d1" ]
      },
      "type" : [ "h-card", "p-location" ]
    } ],
    "published" : [ "2021-10-19T15:21:27+00:00" ],
    "uid" : [ "tag:twitter.com:1450482233802903553" ],
    "url" : [ "https://twitter.com/sheevpaIps/status/1450482233802903553" ],
    "video" : [ "https://video.twimg.com/ext_tw_video/1450482113237635084/pu/vid/640x360/JO6tbq_TkWYhf7eQ.mp4?tag=12" ]
  },
  "type" : [ "h-entry" ]
}
