{
  "properties" : {
    "author" : [ {
      "properties" : {
        "location" : [ {
          "properties" : {
            "name" : [ "🇮🇩 " ]
          },
          "type" : [ "h-card", "p-location" ]
        } ],
        "name" : [ "WILDEST DREAMS HAHA 🧣" ],
        "nickname" : [ "swiftoursonggg" ],
        "numeric-id" : [ "1466185648168218630" ],
        "photo" : [ "https://pbs.twimg.com/profile_images/1592687596513075201/POGzlcjD.jpg" ],
        "published" : [ "2021-12-01T23:21:33+00:00" ],
        "uid" : [ "tag:twitter.com:swiftoursonggg" ],
        "url" : [ "https://twitter.com/swiftoursonggg" ]
      },
      "type" : [ "h-card" ]
    } ],
    "content" : [ "A glimpse into Kanye West’s worst nightmare." ],
    "photo" : [ "https://pbs.twimg.com/media/Fi7nH4-UAAAKRUA.jpg" ],
    "published" : [ "2022-12-02T00:08:14+00:00" ],
    "uid" : [ "tag:twitter.com:1598469049536905216" ],
    "url" : [ "https://twitter.com/swiftoursonggg/status/1598469049536905216" ]
  },
  "type" : [ "h-entry" ]
}
