{
  "children" : [ {
    "properties" : {
      "author" : [ {
        "properties" : {
          "location" : [ {
            "properties" : {
              "name" : [ "Pittsburgh, PA" ]
            },
            "type" : [ "h-card", "p-location" ]
          } ],
          "name" : [ "Scoot 😷" ],
          "nickname" : [ "ImpeachmentHour" ],
          "numeric-id" : [ "3159954231" ],
          "photo" : [ "https://pbs.twimg.com/profile_images/1306689720928346125/ekIo1xnI.jpg" ],
          "published" : [ "2015-04-12T14:34:02+00:00" ],
          "uid" : [ "tag:twitter.com:ImpeachmentHour" ],
          "url" : [ "https://twitter.com/ImpeachmentHour" ]
        },
        "type" : [ "h-card" ]
      } ],
      "content" : [ {
        "html" : "<div style=\"white-space: pre\">Can't repeat this enough! \nThank you so much Joe!!!</div>",
        "value" : "Can't repeat this enough! \nThank you so much Joe!!!"
      } ],
      "photo" : [ "https://pbs.twimg.com/media/FHYyKRgXEBo5JxK.jpg" ],
      "published" : [ "2021-12-24T16:45:56+00:00" ],
      "uid" : [ "tag:twitter.com:1474421091212873733" ],
      "url" : [ "https://twitter.com/ImpeachmentHour/status/1474421091212873733" ]
    },
    "type" : [ "u-quotation-of", "h-cite" ]
  }, {
    "properties" : {
      "name" : [ "twitter.com/impeachmenthou…" ],
      "url" : [ "https://twitter.com/impeachmenthour/status/1474421091212873733" ]
    },
    "type" : [ "h-cite" ]
  } ],
  "properties" : {
    "author" : [ {
      "properties" : {
        "name" : [ "ihla" ],
        "nickname" : [ "taderfxt" ],
        "numeric-id" : [ "1344181693440126977" ],
        "photo" : [ "https://pbs.twimg.com/profile_images/1474393659281838084/M6rxFsNd.jpg" ],
        "published" : [ "2020-12-30T07:21:12+00:00" ],
        "uid" : [ "tag:twitter.com:taderfxt" ],
        "url" : [ "https://twitter.com/taderfxt", "https://libcom.org/files/thomas-sankara-womens-liberation-and-the-african-freedom-struggle.pdf" ]
      },
      "type" : [ "h-card" ]
    } ],
    "content" : [ {
      "html" : "imagine saying this when there are active u.s. and western colonies in the third world, and when oppressed and exploited people are under settler colonial and imperialist regimes that are both funded and political backed by the american empire. absolutely ludicrous.\n<a class=\"tag\" href=\"https://twitter.com/impeachmenthour/status/1474421091212873733\">twitter.com/impeachmenthou…</a>",
      "value" : "imagine saying this when there are active u.s. and western colonies in the third world, and when oppressed and exploited people are under settler colonial and imperialist regimes that are both funded and political backed by the american empire. absolutely ludicrous."
    } ],
    "published" : [ "2021-12-26T04:16:41+00:00" ],
    "uid" : [ "tag:twitter.com:1474957314729787393" ],
    "url" : [ "https://twitter.com/taderfxt/status/1474957314729787393" ]
  },
  "type" : [ "h-entry" ]
}
