{
  "type" : [ "h-entry" ],
  "properties" : {
    "name" : [ "Alexander Hay (@alexanderhay@mastodon.social)" ],
    "summary" : [ "Attached: 1 image\n\nApparently, the #DailyMail has just launched \"Woke Watch\", where red faced pillocks send in angry e-mails, complaining about transgender asylum seekers giving their house prices pronoun cancer, or something.\n\nAnyway, UNDER NO CIRCUMSTANCES should one e-mail wokewatch@dailymail.co.uk to #Troll, #Shitpost or just plain take the piss. No, that would be WRONG. Oh, for shame!\n\n#News #UK #Media" ],
    "featured" : [ "https://files.mastodon.social/media_attachments/files/110/831/571/213/140/816/original/96f8ccb325cbb1ce.png" ],
    "url" : [ "https://mastodon.social/@alexanderhay/110831590101527176" ]
  }
}
