{
  "type" : [ "h-entry" ],
  "properties" : {
    "name" : [ "Scott Kellum :typetura: (@scott@typetura.social)" ],
    "summary" : [ "Had an awesome job lined up. High profile editorial, Ghost CMS, tight timeline but healthy budget, awesome producer.\n\nFound out the client is a Jan 6th insurrection apologist and had to decline. I’m not picky about work right now but I draw the line at treason and fascism. \n\nAnyway, if anyone wants to do a project together, I have availability!" ],
    "url" : [ "https://typetura.social/@scott/110950843660087232" ]
  }
}
