{
  "type" : [ "h-entry" ],
  "properties" : {
    "name" : [ "FOSSY 2023 with Denver Gingerich" ],
    "summary" : [ "Denver discusses JMP's goal to make phone numbers as flexible as emails, his role at Software Freedom Conservancy, and software compliance controversies." ],
    "featured" : [ "https://assets.fireside.fm/file/fireside-images/podcasts/images/2/27729c65-f4a6-4496-8c86-820e7f13b285/episodes/5/5d02d114-1c87-4ba6-a521-15803ea1ec45/cover_medium.jpg?v=1" ],
    "audio" : [ "https://aphid.fireside.fm/d/1437767933/27729c65-f4a6-4496-8c86-820e7f13b285/5d02d114-1c87-4ba6-a521-15803ea1ec45.mp3" ],
    "author" : [ {
      "type" : [ "h-card" ],
      "properties" : {
        "name" : [ "SustainOSS" ]
      }
    } ],
    "url" : [ "https://podcast.sustainoss.org/195" ]
  }
}
