{
  "type" : [ "h-entry" ],
  "properties" : {
    "name" : [ "Co-maintaining openness" ],
    "summary" : [ "Reviving vintage tech is about more than just nostalgia, @janaboruta discusses open source community building for startups, and the value of collaborative maintainership now on The ReadME Project:" ],
    "featured" : [ "https://images.ctfassets.net/s5uo95nf6njh/4ZfmVAn18WMmo5IVNl5Ng7/0443b18c850feaf0d7223324cb017fb9/1200x630-RMP-E_21-Twitter-Title__2_.jpg" ],
    "url" : [ "https://github.com/readme/podcast/comaintaining-openness" ]
  }
}
